ano_optimizer/__init__.py
ano_optimizer/ano_pytorch.py
ano_optimizer/tensorflow.py
ano_optimizer-1.0.0.dist-info/licenses/LICENSE
ano_optimizer-1.0.0.dist-info/METADATA
ano_optimizer-1.0.0.dist-info/WHEEL
ano_optimizer-1.0.0.dist-info/top_level.txt
ano_optimizer-1.0.0.dist-info/RECORD
