Metadata-Version: 2.4
Name: ano-optimizer
Version: 1.0.0
Summary: Ano optimizer official implementation
Author-email: Adrien Kegreisz <adrien.kegreisz@gmail.com>
License: MIT
Requires-Python: >=3.8
License-File: LICENSE
Requires-Dist: torch>=2.0
Provides-Extra: tensorflow
Requires-Dist: tensorflow>=2.14; extra == "tensorflow"
Dynamic: license-file
